PIKACHU/__init__.py
PIKACHU/consumer.py
PIKACHU/producor.py
PIKACHU/utils/__init__.py
PIKACHU/utils/py2.py
PIKACHU/utils/py3.py
PI_KA_CHU-0.2.5.data/data/LICENSE
PI_KA_CHU-0.2.5.dist-info/LICENSE.txt
PI_KA_CHU-0.2.5.dist-info/METADATA
PI_KA_CHU-0.2.5.dist-info/RECORD
PI_KA_CHU-0.2.5.dist-info/WHEEL
PI_KA_CHU-0.2.5.dist-info/top_level.txt
