Metadata-Version: 2.1
Name: PI-KA-CHU
Version: 0.2.5
Summary: a PIKA based, Cuter and more Human rabbitmq queue Utility (´_ゝ`)
Home-page: https://github.com/smilefufu/PIKACHU
Author: fufu
Author-email: fufu.bluesand@gmail.com
License: UNKNOWN
Platform: UNKNOWN
Classifier: License :: OSI Approved :: BSD License
Classifier: Programming Language :: Python :: 2
Classifier: Programming Language :: Python :: 2.7
Classifier: Programming Language :: Python :: 3
Classifier: Programming Language :: Python :: 3.4
Classifier: Programming Language :: Python :: 3.5
Classifier: Programming Language :: Python :: 3.6
Classifier: Operating System :: OS Independent
Requires-Dist: pika
